{
    "Navigator": {
        "username": "NamiSwan",
        "password": "CatBurglar"
    },
    "Doctor": {
        "username": "TonyTonyChopper",
        "password": "HumanHumanFruit"
    },
    "SurgeonofDeath": {
        "username": "TrafalgarLaw",
        "password": "OpeOpeFruit"
    },
    "Archeologist": {
        "username": "NicoRobin",
        "password": "FlowerFlowerFruit"
    },
    "ShipWright": {
        "username": "FrankieGusto",
        "password": "CuttyFlam"
    },
    "GreatestSwordsman": {
        "username": "RoronoaZoro",
        "password": "3SwordStyle"
    },
    "SnakePrincess": {
        "username": "BoaHancock",
        "password": "LoveLoveFruit"
    }
}